forestadmin/fastapi_agent/__init__.py
forestadmin/fastapi_agent/agent.py
forestadmin/fastapi_agent/exception.py
forestadmin/fastapi_agent/routes.py
forestadmin/fastapi_agent/settings.py
forestadmin/fastapi_agent/utils/__init__.py
forestadmin/fastapi_agent/utils/requests.py
forestadmin_agent_fastapi-1.9.0b1.dist-info/METADATA
forestadmin_agent_fastapi-1.9.0b1.dist-info/WHEEL
forestadmin_agent_fastapi-1.9.0b1.dist-info/RECORD
