Metadata-Version: 2.1
Name: forestadmin-agent-fastapi
Version: 1.9.0b1
Summary: fastapi agent for forestadmin python agent
Home-page: https://www.forestadmin.com
Author: Julien Barreau
Author-email: julien.barreau@forestadmin.com
Requires-Python: >=3.8,<3.13
Classifier: Programming Language :: Python :: 3
Classifier: Programming Language :: Python :: 3.8
Classifier: Programming Language :: Python :: 3.9
Classifier: Programming Language :: Python :: 3.10
Classifier: Programming Language :: Python :: 3.11
Classifier: Programming Language :: Python :: 3.12
Requires-Dist: backports.zoneinfo[tzdata] (>=0.2.1,<0.3.0) ; python_version < "3.9"
Requires-Dist: fastapi (>=0.110.0)
Requires-Dist: forestadmin-agent-toolkit (==1.9.0-beta.1)
Requires-Dist: typing-extensions (>=4.2,<5.0)
Project-URL: Documentation, https://docs.forestadmin.com/developer-guide-agents-python/
Project-URL: Repository, https://github.com/ForestAdmin/agent-python
